configcat_openfeature_provider/__init__.py
configcat_openfeature_provider/provider.py
configcat_openfeature_provider/py.typed
configcat_openfeature_provider-1.0.0.dist-info/METADATA
configcat_openfeature_provider-1.0.0.dist-info/WHEEL
configcat_openfeature_provider-1.0.0.dist-info/licenses/LICENSE
configcat_openfeature_provider-1.0.0.dist-info/RECORD
