Metadata-Version: 2.3
Name: configcat-openfeature-provider
Version: 1.0.0
Summary: ConfigCat OpenFeature Provider for Python
Project-URL: Homepage, https://github.com/configcat/openfeature-python
Project-URL: Repository, https://github.com/configcat/openfeature-python.git
Project-URL: Issues, https://github.com/configcat/openfeature-python/issues
Project-URL: Changelog, https://github.com/configcat/openfeature-python/blob/main/CHANGELOG.md
Author-email: ConfigCat <developer@configcat.com>
License: MIT License
License-File: LICENSE
Keywords: configcat,feature,flags,openfeature,provider,toggles
Classifier: Intended Audience :: Developers
Classifier: License :: OSI Approved :: MIT License
Classifier: Operating System :: OS Independent
Classifier: Programming Language :: Python :: 3
Classifier: Programming Language :: Python :: 3.8
Classifier: Programming Language :: Python :: 3.9
Classifier: Programming Language :: Python :: 3.10
Classifier: Programming Language :: Python :: 3.11
Classifier: Programming Language :: Python :: 3.12
Classifier: Topic :: Software Development
Classifier: Topic :: Software Development :: Libraries
Requires-Python: >=3.8
Requires-Dist: configcat-client>=9
Requires-Dist: openfeature-sdk>=0.7
